_posixsubprocess32.so
subprocess32.py
subprocess32-3.5.2.dist-info/METADATA
subprocess32-3.5.2.dist-info/RECORD
subprocess32-3.5.2.dist-info/WHEEL
subprocess32-3.5.2.dist-info/top_level.txt
