Metadata-Version: 1.2
Name: subprocess32
Version: 3.5.2
Summary: A backport of the subprocess module from Python 3 for use on 2.x.
Home-page: https://github.com/google/python-subprocess32
Author: Gregory P. Smith
Author-email: greg@krypto.org
License: PSF license
Platform: UNKNOWN
Classifier: Intended Audience :: Developers
Classifier: Topic :: Software Development :: Libraries
Classifier: Development Status :: 5 - Production/Stable
Classifier: License :: OSI Approved :: Python Software Foundation License
Classifier: Operating System :: MacOS
Classifier: Operating System :: MacOS :: MacOS X
Classifier: Operating System :: POSIX
Classifier: Operating System :: POSIX :: BSD
Classifier: Operating System :: POSIX :: Linux
Classifier: Operating System :: POSIX :: SunOS/Solaris
Classifier: Programming Language :: Python :: 2.6
Classifier: Programming Language :: Python :: 2.7
Classifier: Programming Language :: Python :: 2 :: Only
Classifier: Programming Language :: Python :: Implementation :: CPython
Requires-Python: >=2.6, !=3.0.*, !=3.1.*, !=3.2.*, <4
